pytest_result_sender_lj-0.1.7.dist-info/METADATA
pytest_result_sender_lj-0.1.7.dist-info/WHEEL
pytest_result_sender_lj-0.1.7.dist-info/entry_points.txt
pytest_result_sender_lj/__init__.py
pytest_result_sender_lj/plugin.py
pytest_result_sender_lj-0.1.7.dist-info/RECORD
