Metadata-Version: 2.1
Name: pytest-result-sender-lj
Version: 0.1.7
Summary: Default template for PDM package
Author-Email: jinlyu <lvjin@5i5j.com>
License: MIT
Requires-Python: >=3.10
Requires-Dist: pytest>=8.3.4
Requires-Dist: requests>=2.32.3
